Workbook

Sheet Cover
B2: TEST CASE
B4: Project Name | C4: Fly Booking System | F4: Creator
B5: Project Code | C5: FLYBOOKING | F5: Reviewer/Approver
B6: Document Code | C6: =C5&"_"&"XXX"&"_"&"vx.x" -> FLYBOOKING_XXX_vx.x | F6: Date
F7: Version
B9: History
B10: No | C10: Function Name | D10: Sheet Name | E10: A, D, M | F10: Description | G10: Version | H10: Reference
B11: 1 | C11: Đặt vé máy bay (Search - Results - Details - Confirm) | D11: FlyBookingTestCase!A1 | H11: Fly_Booking_Requirements_V6.docx

Sheet FlyBookingTestCase
A2: Module Code | B2: FLY | H2: Pass
A3: Test requirement | B3: Kiểm tra chức năng đặt vé máy bay (Search, Search Results, Personal Details, Confirm) - Fly_Booking_Requirements_V6.docx | H3: Fail
A4: Environment | B4: Pass | C4: Fail | D4: Untested | E4: N/A | F4: Total
A5: IE | B5: =COUNTIF(I15:I1003,"Pass") -> 0 | C5: =COUNTIF(I15:I1003,"Fail") -> 0 | D5: =COUNTIF(I15:I1003,"Untested") -> 0 | E5: =COUNTIF(I15:I1003,"N/A") -> 51 | F5: =COUNTA(B15:B1003) -> 51
A6: Chrome | B6: =COUNTIF(R15:R1003,"Pass") -> 44 | C6: =COUNTIF(R15:R1003,"Fail") -> 6 | D6: =COUNTIF(R15:R1003,"Untested") -> 1 | E6: =COUNTIF(R15:R1003,"N/A") -> 0 | F6: =COUNTA(B15:B1003) -> 51
A7: Firefox | B7: =COUNTIF(S15:S1003,"Pass") -> 0 | C7: =COUNTIF(S15:S1003,"Fail") -> 0 | D7: =COUNTIF(S15:S1003,"Untested") -> 0 | E7: =COUNTIF(S15:S1003,"N/A") -> 51 | F7: =COUNTA(B15:B1003) -> 51 | H7: N/A
A8: Tester
A9: Date
A11: ID | B11: Test Case Description | C11: Test Case Procedure | D11: Pre - Condition | E11: Expected Result | F11: Test Data | G11: Test Result | I11: Test Results
I13: IE | R13: Chrome | S13: Firefox
A15: SEARCH - Nơi đi / Nơi đến
A16: FLY_01 | B16: Gõ từ 3 ký tự trở lên ở trường Nơi đi hiển thị gợi ý | C16: 1. Vào màn hình Search 2. Gõ 3 ký tự vào trường Nơi đi, ví dụ 'HAN' | D16: Đang ở màn hình Search | E16: Hệ thống hiển thị danh sách gợi ý gồm Tên và Mã sân bay, ví dụ 'Noi Bai airport (HAN)' | F16: Nơi đi: HAN | G16: Danh sách gợi ý hiển thị đúng định dạng 'Tên (Mã)', ví dụ 'Noi Bai airport (HAN)'. | I16: N/A | N16: Pass | R16: Pass | S16: N/A
A17: FLY_02 | B17: Gõ dưới 3 ký tự ở Nơi đi không hiện gợi ý | C17: 1. Gõ 1-2 ký tự vào trường Nơi đi | D17: Đang ở màn hình Search | E17: Hệ thống không hiển thị danh sách gợi ý | F17: Nơi đi: HA | G17: Gõ 2 ký tự chưa thấy gợi ý nào xuất hiện, đúng kỳ vọng. | I17: N/A | N17: Pass | R17: Pass | S17: N/A
A18: FLY_03 | B18: Chọn Nơi đi trùng với Nơi đến | C18: 1. Chọn Nơi đi = HAN 2. Chọn Nơi đến = HAN 3. Điền các trường còn lại và bấm Search | D18: Đang ở màn hình Search | E18: Hệ thống báo lỗi Nơi đi và Nơi đến phải khác nhau, không cho tìm kiếm | F18: Nơi đi=HAN, Nơi đến=HAN | G18: Hệ thống báo lỗi 'Departure and Destination must be different', không cho tìm kiếm. | I18: N/A | N18: Pass | R18: Pass | S18: N/A
A19: FLY_04 | B19: Không nhập Nơi đi hoặc Nơi đến rồi bấm Search | C19: 1. Bỏ trống Nơi đi (hoặc Nơi đến) 2. Điền các trường còn lại 3. Bấm Search | D19: Đang ở màn hình Search | E19: Hệ thống báo lỗi 'Xin hãy thông tin/ Please fulfill the input' | F19: Nơi đi: (trống) | G19: Hệ thống hiển thị đúng thông báo 'Please fulfill the input'. | I19: N/A | N19: Pass | R19: Pass | S19: N/A
A20: SEARCH - Ngày đi / Ngày về | G20: Ô nhập ngày không nhận ký tự bàn phím, chỉ mở Calendar khi click, đúng spec. | I20: N/A | N20: Pass | R20: Pass | S20: N/A
A21: FLY_05 | B21: Chỉ cho chọn Ngày đi qua Calendar, không cho gõ tay | C21: 1. Click vào trường Ngày đi 2. Thử gõ tay ngày bằng bàn phím | D21: Đang ở màn hình Search | E21: Hệ thống không cho gõ tay, chỉ cho chọn qua Calendar popup | F21: Gõ thử: 12/30/2026 | G21: Chọn One way: trường Ngày về bị ẩn ngay lập tức. | I21: N/A | N21: Pass | R21: Pass | S21: N/A
A22: FLY_06 | B22: Chọn One way thì ẩn trường Ngày về | C22: 1. Chọn option One way | D22: Đang ở màn hình Search | E22: Trường Ngày về bị ẩn, chỉ hiện Ngày đi | F22: Trip type: One way | G22: Chọn Round trip: trường Ngày về hiện ra; nếu để trống và bấm Search, hệ thống CHƯA báo lỗi riêng cho Ngày về mà chỉ báo chung 'Please fulfill the input' - chấp nhận được nhưng thông báo chưa cụ thể về trường bị thiếu. | I22: N/A | N22: Pass | R22: Pass | S22: N/A
A23: FLY_07 | B23: Chọn Round trip thì hiện và bắt buộc Ngày về | C23: 1. Chọn option Round trip 2. Không chọn Ngày về 3. Điền các trường còn lại và bấm Search | D23: Đang ở màn hình Search | E23: Trường Ngày về được hiển thị; hệ thống báo lỗi bắt buộc chọn Ngày về nếu để trống | F23: Trip type: Round trip | G23: Hệ thống VẪN CHO tạo tìm kiếm thành công dù Ngày về (19/12) trước Ngày đi (20/12); không hiện thông báo 'Ngày về phải sau ngày đi' như spec yêu cầu. | I23: N/A | N23: Fail | R23: Fail | S23: N/A
A24: FLY_08 | B24: Chọn Ngày về trước hoặc bằng Ngày đi | C24: 1. Chọn Round trip 2. Chọn Ngày đi = 20/12/2026 3. Chọn Ngày về = 20/12/2026 hoặc sớm hơn 4. Bấm Search | D24: Đã chọn Round trip | E24: Hệ thống báo lỗi 'Ngày về phải sau ngày đi' | F24: Ngày đi=20/12/2026, Ngày về=19/12/2026 | G24: Tìm kiếm thành công, không báo lỗi với Ngày về hợp lệ sau Ngày đi. | I24: N/A | N24: Pass | R24: Pass | S24: N/A
A25: FLY_09 | B25: Chọn Ngày về hợp lệ (sau Ngày đi) | C25: 1. Chọn Round trip 2. Chọn Ngày đi = 20/12/2026, Ngày về = 25/12/2026 3. Bấm Search | D25: Đã chọn Round trip | E25: Hệ thống cho phép tìm kiếm, không báo lỗi | F25: Ngày đi=20/12/2026, Ngày về=25/12/2026
A26: SEARCH - Số lượng hành khách | G26: Adults=1, Child=0, Infant=0 hiển thị đúng mặc định. | I26: N/A | N26: Pass | R26: Pass | S26: N/A
A27: FLY_10 | B27: Giá trị mặc định của số lượng hành khách | C27: 1. Mở màn hình Search, quan sát các ô Adults/Child/Infant | D27: Đang ở màn hình Search | E27: Adults mặc định = 1, Child mặc định = 0, Infant mặc định = 0 | F27: (không nhập gì) | G27: Nút '+' ở Adults bị vô hiệu hóa (disable) khi đã đạt giá trị 3, và nút '-' disable khi ở giá trị 1; không cho vượt ngưỡng. | I27: N/A | N27: Pass | R27: Pass | S27: N/A
A28: FLY_11 | B28: Nhập Adults nhỏ hơn 1 hoặc lớn hơn 3 | C28: 1. Thử giảm Adults xuống 0 hoặc tăng lên 4 | D28: Đang ở màn hình Search | E28: Hệ thống chặn, không cho vượt qua khoảng min=1 max=3 (có thể cấu hình được) | F28: Adults: 0 hoặc 4 | G28: Hệ thống KHÔNG kiểm tra ràng buộc 'người lớn >= trẻ em'; vẫn cho tìm kiếm thành công với Adults=1, Child=2. | I28: N/A | N28: Fail | R28: Fail | S28: N/A
A29: FLY_12 | B29: Tổng số trẻ em vượt quá số người lớn | C29: 1. Đặt Adults = 1 2. Đặt Child + Infant > 1 (ví dụ Child=2) 3. Bấm Search | D29: Đang ở màn hình Search | E29: Hệ thống báo lỗi vì 1 người lớn chỉ được đi cùng tối đa 1 trẻ em | F29: Adults=1, Child=2 | G29: Tìm kiếm thành công với Adults=1, Child=1, không báo lỗi. | I29: N/A | N29: Pass | R29: Pass | S29: N/A
A30: FLY_13 | B30: Số lượng hành khách hợp lệ (Adults=1, Child=1) | C30: 1. Đặt Adults=1, Child=1, Infant=0 2. Điền các trường còn lại và bấm Search | D30: Đang ở màn hình Search | E30: Hệ thống cho phép tìm kiếm bình thường | F30: Adults=1, Child=1, Infant=0 | G30: Vì UI dùng stepper (không cho giảm dưới 1), không thể tạo trường hợp Adults=0 trên giao diện; cần Dev xác nhận có con đường nào (ví dụ qua URL/API) để đặt 0 hay không. Tạm để Untested. | I30: N/A | N30: Untested | R30: Untested | S30: N/A
A31: FLY_14 | B31: Bấm Search khi tổng số người = 0 | C31: 1. Đặt Adults=0 (nếu hệ thống cho phép giảm về 0 trước khi validate) 2. Bấm Search | D31: Đang ở màn hình Search | E31: Hệ thống báo lỗi 'Xin hãy thông tin' vì số lượng người = 0 | F31: Adults=0
A32: SEARCH - Loại chuyến đi & Hạng vé | G32: Mặc định đúng là One way và Economy khi vào màn hình Search. | I32: N/A | N32: Pass | R32: Pass | S32: N/A
A33: FLY_15 | B33: Giá trị mặc định của Loại chuyến đi và Hạng vé | C33: 1. Mở màn hình Search, quan sát | D33: Đang ở màn hình Search | E33: Mặc định là One way và hạng Economy | F33: (không nhập gì) | G33: Chọn được Business/First, dropdown cập nhật đúng giá trị đã chọn. | I33: N/A | N33: Pass | R33: Pass | S33: N/A
A34: FLY_16 | B34: Chọn các hạng vé khác Economy | C34: 1. Mở dropdown Hạng vé 2. Chọn Business hoặc First | D34: Đang ở màn hình Search | E34: Hệ thống cho phép chọn và cập nhật đúng lựa chọn (Business/First) | F34: Hạng vé: Business
A35: SEARCH - Nút Search (validate tổng hợp) | G35: Bấm Search khi thiếu cả 3 trường: hệ thống báo 'Please fulfill the input', không điều hướng sang trang kết quả. | I35: N/A | N35: Pass | R35: Pass | S35: N/A
A36: FLY_17 | B36: Bấm Search khi thiếu nhiều trường bắt buộc cùng lúc | C36: 1. Bỏ trống cả Nơi đi, Nơi đến, Ngày đi 2. Bấm Search | D36: Đang ở màn hình Search | E36: Hệ thống báo lỗi 'Xin hãy thông tin/ Please fulfill the input', không thực hiện tìm kiếm | F36: Tất cả đều để trống | G36: Tìm kiếm thành công, điều hướng sang Search Results với danh sách chuyến bay HAN-SGN hiển thị đầy đủ. | I36: N/A | N36: Pass | R36: Pass | S36: N/A
A37: FLY_18 | B37: Tìm kiếm thành công với dữ liệu hợp lệ | C37: 1. Điền đầy đủ: Nơi đi=HAN, Nơi đến=SGN, Ngày đi=20/12/2026, Adults=1, One way, Economy 2. Bấm Search | D37: Đang ở màn hình Search | E37: Hệ thống chuyển sang màn hình Search Results, hiển thị danh sách chuyến bay và giá vé tương ứng | F37: HAN -> SGN, 20/12/2026, Adults=1
A38: SEARCH RESULTS - Bộ lọc (Filter) | G38: Tất cả checkbox Route Stops và Airlines ở trạng thái uncheck mặc định khi vào trang. | I38: N/A | N38: Pass | R38: Pass | S38: N/A
A39: FLY_19 | B39: Các ô filter mặc định ở trạng thái uncheck | C39: 1. Vào màn hình Search Results sau khi tìm kiếm | D39: Đã có kết quả tìm kiếm hiển thị | E39: Tất cả checkbox trong Route Stops và Airlines đều ở trạng thái uncheck | F39: (không thao tác) | G39: Sau khi tick 'Direct', danh sách chỉ còn các chuyến bay không dừng, đúng kỳ vọng. | I39: N/A | N39: Pass | R39: Pass | S39: N/A
A40: FLY_20 | B40: Lọc theo 1 điều kiện Route Stops | C40: 1. Tick chọn 'Direct' | D40: Đang ở màn hình Search Results | E40: Danh sách chỉ hiện các chuyến bay không qua trạm dừng (non-stop) | F40: Route Stops: Direct | G40: Tick Direct + 1 hãng bay: danh sách lọc đúng cả 2 điều kiện (AND giữa nhóm), đúng như Requirement Log đã xác nhận. | I40: N/A | N40: Pass | R40: Pass | S40: N/A
A41: FLY_21 | B41: Lọc kết hợp Route Stops và Airlines (AND giữa 2 nhóm) | C41: 1. Tick 'Direct' trong Route Stops 2. Tick 1 hãng bay cụ thể trong Airlines | D41: Đang ở màn hình Search Results | E41: Danh sách chỉ hiện chuyến bay THỎA CẢ HAI điều kiện: không dừng + đúng hãng bay đã chọn | F41: Route Stops: Direct, Airlines: Delta Air Lines | G41: Đổi Ngày đi và bấm lại Search: danh sách Available Flights cập nhật đúng, tuy nhiên phần 'Date Availability' đề cập trong spec KHÔNG hiển thị trên giao diện thực tế (có thể là tính năng chưa triển khai hoặc spec chưa khớp UI). | I41: N/A | N41: Fail | R41: Fail | S41: N/A
A42: FLY_22 | B42: Bấm lại nút Search ở Search Results để cập nhật kết quả | C42: 1. Thay đổi điều kiện tra cứu (ví dụ đổi Ngày đi) 2. Bấm nút Search trên màn hình Search Results | D42: Đang ở màn hình Search Results | E42: Danh sách chuyến bay (Available Flights) và Date Availability được cập nhật theo điều kiện mới | F42: Đổi Ngày đi sang ngày khác
A43: SEARCH RESULTS - Danh sách chuyến bay | G43: Các trường hiển thị đầy đủ: icon+tên hãng bay, mã chuyến bay, tuyến bay, giờ đi/đến, tag non-stop/transit, giá USD - đúng spec. | I43: N/A | N43: Pass | R43: Pass | S43: N/A
A44: FLY_23 | B44: Kiểm tra thông tin hiển thị của 1 chuyến bay | C44: 1. Quan sát 1 dòng kết quả bất kỳ trong danh sách | D44: Đã có kết quả tìm kiếm | E44: Hiển thị đầy đủ: icon+tên hãng bay, mã số chuyến bay, thông tin đường bay (ví dụ HAN -> SGN), giờ đi/đến, đặc điểm non-stop/transit, giá vé USD | F44: (quan sát UI) | G44: Nút Book Now ở tất cả các dòng đều ở trạng thái enable. | I44: N/A | N44: Pass | R44: Pass | S44: N/A
A45: FLY_24 | B45: Nút Book Now luôn ở trạng thái enable | C45: 1. Quan sát nút Book Now trên các dòng kết quả | D45: Đã có kết quả tìm kiếm | E45: Nút Book Now luôn enable trên mọi dòng, không bị mờ (disable) | F45: (quan sát UI) | G45: Bấm Book Now điều hướng đúng sang Personal Details, giữ nguyên thông tin chuyến bay đã chọn. | I45: N/A | N45: Pass | R45: Pass | S45: N/A
A46: FLY_25 | B46: Bấm Book Now chuyển sang màn hình Personal Details | C46: 1. Click nút Book Now trên 1 chuyến bay bất kỳ | D46: Đã có kết quả tìm kiếm | E46: Hệ thống điều hướng sang màn hình nhập Personal Details, giữ đúng thông tin chuyến bay đã chọn | F46: Chọn 1 chuyến bay bất kỳ
A47: DETAILS - Personal Details | G47: Bỏ trống First Name và bấm Confirm: hiển thị 'This field is required' ngay dưới textbox First Name. | I47: N/A | N47: Pass | R47: Pass | S47: N/A
A48: FLY_26 | B48: Bỏ trống trường bắt buộc (First Name/Last Name/Email) | C48: 1. Bỏ trống First Name 2. Điền các trường khác 3. Bấm Confirm This Booking | D48: Đang ở màn hình Personal Details | E48: Hiển thị error message dưới textbox: 'This field is required' | F48: First Name: (trống) | G48: Textbox chặn nhập quá 50 ký tự, đúng kỳ vọng. | I48: N/A | N48: Pass | R48: Pass | S48: N/A
A49: FLY_27 | B49: Nhập vượt quá 50 ký tự cho các trường text | C49: 1. Nhập chuỗi 51 ký tự vào First Name (hoặc Address) | D49: Đang ở màn hình Personal Details | E49: Hệ thống chặn không cho nhập quá 50 ký tự | F49: First Name: chuỗi 51 ký tự | G49: Ô Mobile chỉ nhận số và dấu '+' ở đầu, từ chối ký tự chữ; tuy nhiên hệ thống KHÔNG giới hạn độ dài 16 ký tự như spec yêu cầu (vẫn cho nhập 20+ số). | I49: N/A | N49: Fail | R49: Fail | S49: N/A
A50: FLY_28 | B50: Nhập Mobile quá 16 ký tự hoặc chứa chữ | C50: 1. Nhập chữ vào trường Mobile 2. Nhập số có độ dài > 16 ký tự | D50: Đang ở màn hình Personal Details | E50: Hệ thống chỉ nhận số (có thể có dấu '+' đầu số), chặn ký tự chữ và giới hạn độ dài 16 | F50: Mobile: 'abc123' hoặc chuỗi 17 chữ số | G50: Gõ 'Viet' vào Country: danh sách lọc đúng ra 'Vietnam'. | I50: N/A | N50: Pass | R50: Pass | S50: N/A
A51: FLY_29 | B51: Tìm kiếm quốc gia trong trường Country | C51: 1. Click vào trường Country 2. Gõ từ khóa tìm kiếm tên quốc gia | D51: Đang ở màn hình Personal Details | E51: Hệ thống lọc và hiển thị danh sách quốc gia phù hợp với từ khóa | F51: Từ khóa: 'Viet' | G51: Nhập coupon nhưng không bấm Apply Coupon, sau đó Confirm: giá tiền không đổi, coupon không được áp dụng, đúng kỳ vọng. | I51: N/A | N51: Pass | R51: Pass | S51: N/A
A52: FLY_30 | B52: Nhập Coupon nhưng không bấm Apply Coupon | C52: 1. Nhập mã coupon vào ô Coupon Code 2. KHÔNG bấm Apply Coupon 3. Bấm Confirm This Booking | D52: Đang ở màn hình Personal Details | E52: Coupon không được áp dụng (coi như chưa nhập), giá tiền không đổi | F52: Coupon: SUMMER10 (không bấm Apply) | G52: Bấm Apply Coupon với mã hợp lệ: hệ thống áp dụng giảm giá và cập nhật lại tổng tiền hiển thị. | I52: N/A | N52: Pass | R52: Pass | S52: N/A
A53: FLY_31 | B53: Nhập Coupon hợp lệ và bấm Apply Coupon | C53: 1. Nhập mã coupon hợp lệ 2. Bấm Apply Coupon | D53: Đang ở màn hình Personal Details | E53: Hệ thống áp dụng giảm giá theo giá trị coupon, cập nhật lại tổng tiền | F53: Coupon: SUMMER10 (hợp lệ)
A54: DETAILS - Passengers | G54: Đúng 3 form (trắng/xanh/hồng) hiển thị tương ứng Adult/Child/Infant, đúng số lượng đã chọn ở Search. | I54: N/A | N54: Pass | R54: Pass | S54: N/A
A55: FLY_32 | B55: Số lượng form Passenger khớp với số lượng đã chọn ở Search | C55: 1. Ở bước Search đã chọn Adults=1, Child=1, Infant=1 2. Quan sát màn hình Personal Details | D55: Đã search với Adults=1, Child=1, Infant=1 | E55: Hiển thị đúng 3 khung nhập: 1 form nền trắng (Adult), 1 form nền xanh (Child), 1 form nền hồng (Infant) | F55: Adults=1, Child=1, Infant=1 | G55: Dropdown Age của form Adult chỉ liệt kê giá trị 12-100. | I55: N/A | N55: Pass | R55: Pass | S55: N/A
A56: FLY_33 | B56: Nhập Age cho form Adult (nền trắng) | C56: 1. Click vào trường Age trong form Adult | D56: Đang nhập form Adult | E56: Danh sách tuổi hiển thị chỉ gồm các giá trị từ 12 đến 100 | F56: Form Adult | G56: Dropdown Age của form Child chỉ liệt kê giá trị 4-11. | I56: N/A | N56: Pass | R56: Pass | S56: N/A
A57: FLY_34 | B57: Nhập Age cho form Child (nền xanh) | C57: 1. Click vào trường Age trong form Child | D57: Đang nhập form Child | E57: Danh sách tuổi hiển thị chỉ gồm các giá trị từ 4 đến 11 | F57: Form Child | G57: Dropdown Age của form Infant chỉ liệt kê giá trị 0,1,2,3 (<4). | I57: N/A | N57: Pass | R57: Pass | S57: N/A
A58: FLY_35 | B58: Nhập Age cho form Infant (nền hồng) | C58: 1. Click vào trường Age trong form Infant | D58: Đang nhập form Infant | E58: Danh sách tuổi hiển thị chỉ gồm các giá trị < 4 (3,2,1,0) | F58: Form Infant | G58: Trường Name chặn nhập số và ký tự đặc biệt, chỉ cho chữ Unicode. | I58: N/A | N58: Pass | R58: Pass | S58: N/A
A59: FLY_36 | B59: Nhập Name chứa ký tự không phải Unicode chữ | C59: 1. Nhập số hoặc ký tự đặc biệt vào trường Name của hành khách | D59: Đang nhập thông tin hành khách | E59: Hệ thống chặn, chỉ cho phép nhập ký tự Unicode (chữ cái) | F59: Name: '12345' hoặc 'Nguyen@Van' | G59: Trường Passport Number VẪN CHO nhập dấu cách và một số ký tự đặc biệt như '-', không khớp hoàn toàn với yêu cầu spec (chỉ cho số/chữ). | I59: N/A | N59: Fail | R59: Fail | S59: N/A
A60: FLY_37 | B60: Nhập Passport Number chứa ký tự đặc biệt hoặc khoảng trắng | C60: 1. Nhập ký tự đặc biệt (ví dụ '#', '-') hoặc dấu cách vào Passport Number | D60: Đang nhập thông tin hành khách | E60: Hệ thống chặn, chỉ cho phép số và chữ, không cho ký tự đặc biệt/khoảng trắng | F60: Passport Number: 'AB 123#45'
A61: CONFIRM - Booking Summary / Invoice | G61: Đồng hồ đếm ngược hiển thị đúng định dạng và giảm dần theo giây. | I61: N/A | N61: Pass | R61: Pass | S61: N/A
A62: FLY_38 | B62: Đếm ngược thời gian thanh toán hiển thị và chạy đúng | C62: 1. Vào màn hình Confirm ngay sau khi tạo booking 2. Quan sát bộ đếm thời gian | D62: Đã tạo booking thành công, đang ở màn hình Confirm | E62: Đồng hồ đếm ngược hiển thị đúng định dạng Ngày/Giờ/Phút/Giây và giảm dần theo thời gian thực | F62: (quan sát UI trong 1-2 phút) | G62: Trạng thái invoice hiển thị 'UNPAID' màu đỏ ngay khi vào màn hình. | I62: N/A | N62: Pass | R62: Pass | S62: N/A
A63: FLY_39 | B63: Trạng thái invoice ban đầu là UNPAID | C63: 1. Quan sát trạng thái invoice ngay khi vào màn hình Confirm | D63: Chưa thực hiện thanh toán | E63: Nhãn trạng thái hiển thị 'UNPAID' | F63: (quan sát UI) | G63: Invoice Date = 11/03/2026, Due Date hiển thị = 11/04/2026, đúng công thức +1 tháng. | I63: N/A | N63: Pass | R63: Pass | S63: N/A
A64: FLY_40 | B64: Due Date = Invoice Date + 1 tháng | C64: 1. Quan sát Invoice Date và Due Date trên màn hình Confirm | D64: Đã có invoice được tạo | E64: Due Date đúng bằng Invoice Date cộng thêm 1 tháng | F64: Invoice Date: 11/03/2026 -> Due Date kỳ vọng: 11/04/2026 | G64: Đối chiếu số liệu: Total Amount = Deposit Now + Tax & VAT, khớp chính xác. | I64: N/A | N64: Pass | R64: Pass | S64: N/A
A65: FLY_41 | B65: Tổng tiền Total Amount = Deposit + Tax & VAT | C65: 1. Quan sát 3 giá trị Deposit Now, Tax & VAT (10%), Total Amount | D65: Đã có invoice được tạo | E65: Total Amount đúng bằng tổng của Deposit Now và Tax & VAT (Tax = 10% của Deposit) | F65: (đối chiếu số liệu trên UI) | G65: File PDF và PNG tải về đầy đủ thông tin, không bị xô lệch; chức năng Print mở đúng hộp thoại in của trình duyệt. | I65: N/A | N65: Pass | R65: Pass | S65: N/A
A66: FLY_42 | B66: Download Invoice dạng PNG/PDF và Print | C66: 1. Bấm Download invoice (PNG) 2. Bấm Download PDF 3. Bấm Print | D66: Đã có invoice được tạo | E66: File PNG/PDF tải về đầy đủ thông tin invoice, không bị xô lệch; chức năng Print mở đúng hộp thoại in của trình duyệt | F66: (thực hiện trên invoice bất kỳ)
A67: CONFIRM - Thanh toán Pay on Arrival | G67: Bấm Ok trên popup: hệ thống hiện đúng message 'YOUR BOOKING STATUS IS RESERVED...' và cập nhật trạng thái. | I67: N/A | N67: Pass | R67: Pass | S67: N/A
A68: FLY_43 | B68: Chọn Pay on Arrival và xác nhận Ok | C68: 1. Bấm PAY ON ARRIVAL 2. Popup xác nhận hiện ra, bấm Ok | D68: Đang ở màn hình Confirm, invoice đang UNPAID | E68: Hệ thống hiển thị message 'YOUR BOOKING STATUS IS RESERVED...' và cập nhật trạng thái thanh toán tương ứng | F68: (thao tác trên invoice bất kỳ) | G68: Bấm Cancel: popup đóng lại, trạng thái invoice không đổi (UNPAID). | I68: N/A | N68: Pass | R68: Pass | S68: N/A
A69: FLY_44 | B69: Chọn Pay on Arrival và bấm Cancel trên popup | C69: 1. Bấm PAY ON ARRIVAL 2. Popup xác nhận hiện ra, bấm Cancel | D69: Đang ở màn hình Confirm | E69: Popup đóng lại, trạng thái invoice không đổi (vẫn là UNPAID) | F69: (thao tác trên invoice bất kỳ)
A70: CONFIRM - Thanh toán Pay Now | G70: Chọn Bank Transfer: hiển thị đầy đủ thông tin tài khoản ngân hàng công ty. | I70: N/A | N70: Pass | R70: Pass | S70: N/A
A71: FLY_45 | B71: Chọn phương thức Bank Transfer | C71: 1. Bấm PAY NOW 2. Chọn phương thức Bank Transfer | D71: Đang ở màn hình Confirm | E71: Hệ thống hiển thị thông tin tài khoản ngân hàng của công ty để khách chuyển khoản | F71: Payment method: Bank Transfer | G71: Bỏ trống CVV và bấm thanh toán: hệ thống báo lỗi thiếu thông tin, không cho tiếp tục. | I71: N/A | N71: Pass | R71: Pass | S71: N/A
A72: FLY_46 | B72: Nhập thiếu thông tin thẻ khi chọn Credit Card/Visa | C72: 1. Bấm PAY NOW, chọn Credit Card 2. Bỏ trống 1 trường (ví dụ CVV) 3. Bấm thanh toán | D72: Đã chọn phương thức Credit Card | E72: Hệ thống báo lỗi thiếu thông tin, không cho thanh toán | F72: Số thẻ: đủ, CVV: (trống) | G72: Nhập số thẻ 12 chữ số: hệ thống báo lỗi số thẻ không hợp lệ. | I72: N/A | N72: Pass | R72: Pass | S72: N/A
A73: FLY_47 | B73: Nhập Số thẻ không đủ 16 chữ số | C73: 1. Chọn Credit Card 2. Nhập Số thẻ chỉ 12 chữ số | D73: Đã chọn phương thức Credit Card | E73: Hệ thống báo lỗi số thẻ không hợp lệ | F73: Số thẻ: '123456789012' | G73: Nhập CVV 2 chữ số: hệ thống báo lỗi CVV không hợp lệ. | I73: N/A | N73: Pass | R73: Pass | S73: N/A
A74: FLY_48 | B74: Nhập CVV không đủ 3 chữ số | C74: 1. Chọn Credit Card 2. Nhập CVV chỉ 2 chữ số | D74: Đã chọn phương thức Credit Card | E74: Hệ thống báo lỗi CVV không hợp lệ | F74: CVV: '12' | G74: Nhập tháng/năm hết hạn 01/2020 (đã quá hạn): hệ thống VẪN CHO thanh toán tiếp tục mà không báo lỗi 'thẻ đã hết hạn'. | I74: N/A | N74: Fail | R74: Fail | S74: N/A
A75: FLY_49 | B75: Nhập tháng/năm hết hạn thẻ đã quá hạn | C75: 1. Chọn Credit Card 2. Nhập tháng/năm hết hạn trước tháng/năm hiện tại | D75: Đã chọn phương thức Credit Card | E75: Hệ thống báo lỗi thẻ đã hết hạn | F75: Tháng/năm hết hạn: 01/2020 | G75: Thanh toán thành công với thẻ hợp lệ: hiển thị đúng message 'Invoice [số] is paid successfully', trạng thái chuyển UNPAID -> PAID. | I75: N/A | N75: Pass | R75: Pass | S75: N/A
A76: FLY_50 | B76: Thanh toán thành công với thông tin thẻ hợp lệ | C76: 1. Chọn Credit Card 2. Nhập đầy đủ thông tin hợp lệ 3. Bấm PAY NOW | D76: Đã nhập đầy đủ thông tin thẻ hợp lệ | E76: Hệ thống hiển thị message 'Invoice [invoice_number] is paid successfully' và cập nhật trạng thái UNPAID -> PAID | F76: Thẻ hợp lệ, còn hạn, đủ 16 số, CVV 3 số | G76: Bấm Pay: hệ thống redirect đúng sang trang thanh toán của Paypal (sandbox). | I76: N/A | N76: Pass | R76: Pass | S76: N/A
A77: FLY_51 | B77: Chọn Paypal chuyển hướng sang trang thanh toán đối tác | C77: 1. Bấm PAY NOW 2. Chọn phương thức Paypal 3. Bấm nút Pay | D77: Đang ở màn hình Confirm | E77: Hệ thống redirect người dùng sang trang thanh toán của Paypal | F77: Payment method: Paypal

Sheet Summary
B1: SUMMARY
B4: No | C4: Module code | D4: Pass | E4: Fail | F4: Untested | G4: N/A | H4: Number of test cases
B5: 1 | C5: =FlyBookingTestCase!B2 -> FLY | D5: =FlyBookingTestCase!B6 -> 44 | E5: =FlyBookingTestCase!C6 -> 6 | F5: =FlyBookingTestCase!D6 -> 1 | G5: =FlyBookingTestCase!E6 -> 0 | H5: =FlyBookingTestCase!F6 -> 51
C8: Sub total | D8: =SUM(D5:D7) -> 44 | E8: =SUM(E5:E7) -> 6 | F8: =SUM(F5:F7) -> 1 | G8: =SUM(G5:G7) -> 0 | H8: =SUM(H5:H7) -> 51
C10: Test coverage | E10: =(D8+E8)*100/(H8-G8) -> 98.039216 | F10: %
C11: Test successful coverage | E11: =D8*100/(H8-G8) -> 86.27451 | F11: %
